README.txt
setup.py
collective/__init__.py
collective.portlet.workflowsteps.egg-info/PKG-INFO
collective.portlet.workflowsteps.egg-info/SOURCES.txt
collective.portlet.workflowsteps.egg-info/dependency_links.txt
collective.portlet.workflowsteps.egg-info/entry_points.txt
collective.portlet.workflowsteps.egg-info/namespace_packages.txt
collective.portlet.workflowsteps.egg-info/not-zip-safe
collective.portlet.workflowsteps.egg-info/requires.txt
collective.portlet.workflowsteps.egg-info/top_level.txt
collective/portlet/__init__.py
collective/portlet/workflowsteps/__init__.py
collective/portlet/workflowsteps/configure.zcml
collective/portlet/workflowsteps/version.txt
collective/portlet/workflowsteps/workflowsteps.pt
collective/portlet/workflowsteps/workflowsteps.py
collective/portlet/workflowsteps/profiles/default/metadata.xml
collective/portlet/workflowsteps/profiles/default/portlets.xml
collective/portlet/workflowsteps/tests/__init__.py
collective/portlet/workflowsteps/tests/base.py
collective/portlet/workflowsteps/tests/test_portlet.py
docs/HISTORY.txt
docs/INSTALL.txt
docs/LICENSE.GPL
docs/LICENSE.txt