Metadata-Version: 1.0
Name: collective.portlet.workflowsteps
Version: 1.0b1
Summary: A Plone portlet for showing 'next steps' in a workflow. May include rich text tied to the workflow state and transitions with descriptions.
Home-page: http://pypi.python.org/pypi//collective.portlet.workflowsteps
Author: Martin Aspeli
Author-email: optilude@gmail.com
License: GPL
Keywords: plone portlet workflow
Platform: UNKNOWN
Classifier: Framework :: Plone
Classifier: Programming Language :: Python
Classifier: Topic :: Software Development :: Libraries :: Python Modules
